{
  "_class": "group",
  "booleanOperation": -1,
  "clippingMaskMode": 0,
  "do_objectID": "3CA959C5-50BB-446E-91E8-85E8305BBCCB",
  "exportOptions": {
    "_class": "exportOptions",
    "do_objectID": "3C9A6242-9A1B-4F63-B32F-4EAE55559CE6",
    "exportFormats": [
    ],
    "includedLayerIds": [
    ],
    "layerOptions": 0,
    "shouldTrim": false
  },
  "frame": {
    "_class": "rect",
    "constrainProportions": false,
    "do_objectID": "59140AD5-1123-4321-A3F7-A609A2DC0F25",
    "height": 19,
    "width": 133,
    "x": 1263,
    "y": 82
  },
  "groupLayout": {
    "_class": "MSImmutableFreeformGroupLayout",
    "do_objectID": "56129470-CDCE-4BE7-B70C-C4A815F81E6F"
  },
  "hasClickThrough": false,
  "hasClippingMask": false,
  "isFixedToViewport": false,
  "isFlippedHorizontal": false,
  "isFlippedVertical": false,
  "isLocked": false,
  "isVisible": true,
  "layerListExpandedType": 0,
  "layers": [
    {
      "class": "text",
      "id": "A0B12310-D268-4689-A4F3-3011B403081A"
    },
    {
      "class": "text",
      "id": "7F24E89F-C822-4F01-B911-A478DB8B2A40"
    }
  ],
  "name": "Group",
  "nameIsFixed": false,
  "resizingConstraint": 63,
  "resizingType": 0,
  "rotation": 0,
  "shouldBreakMaskChain": false,
  "style": {
    "_class": "style",
    "contextSettings": {
      "_class": "graphicsContextSettings",
      "blendMode": 0,
      "do_objectID": "A603931D-26B3-4057-A823-8F5C704777E4",
      "opacity": 0.39
    },
    "do_objectID": "5C23DAD7-19AF-47E5-A8E5-031E6C941140",
    "endMarkerType": 0,
    "miterLimit": 10,
    "startMarkerType": 0,
    "windingRule": 1
  }
}