{
  "_class": "symbolInstance",
  "booleanOperation": -1,
  "clippingMaskMode": 0,
  "do_objectID": "E8562414-B748-4197-9039-0D49FF0547F7",
  "exportOptions": {
    "_class": "exportOptions",
    "do_objectID": "2F25623D-1F52-4706-83FE-9855FE60BBE5",
    "exportFormats": [
    ],
    "includedLayerIds": [
    ],
    "layerOptions": 0,
    "shouldTrim": false
  },
  "frame": {
    "_class": "rect",
    "constrainProportions": false,
    "do_objectID": "E48D9EA0-7FF2-459F-AFFD-E1C65CCDFD6E",
    "height": 30,
    "width": 33,
    "x": 9,
    "y": 5
  },
  "hasClippingMask": false,
  "horizontalSpacing": 0,
  "isFixedToViewport": false,
  "isFlippedHorizontal": false,
  "isFlippedVertical": false,
  "isLocked": false,
  "isVisible": true,
  "layerListExpandedType": 0,
  "name": "Top Bar",
  "nameIsFixed": true,
  "overrideValues": [
    {
      "_class": "overrideValue",
      "do_objectID": "D5E3B8B1-D855-4153-A409-05DEA694B194",
      "overrideName": "9BB2F19B-9F15-4CFE-99E5-EB2D466A48D3_stringValue",
      "value": "María López"
    }
  ],
  "resizingConstraint": 47,
  "resizingType": 0,
  "rotation": 0,
  "scale": 1,
  "shouldBreakMaskChain": false,
  "style": {
    "_class": "style",
    "do_objectID": "D8CF8082-F2C5-49CA-9A9C-1868C825B9B4",
    "endMarkerType": 0,
    "miterLimit": 10,
    "startMarkerType": 0,
    "windingRule": 1
  },
  "symbolID": "636AFABF-D4F5-4C4C-80AE-968478795DFD",
  "verticalSpacing": 0
}