{
  "_class": "symbolInstance",
  "booleanOperation": -1,
  "clippingMaskMode": 0,
  "do_objectID": "14F9B319-7247-4B02-918C-1BFDC20DDFF1",
  "exportOptions": {
    "_class": "exportOptions",
    "do_objectID": "157AB6FD-59BF-48C7-97AA-F073E422FB8C",
    "exportFormats": [
    ],
    "includedLayerIds": [
    ],
    "layerOptions": 0,
    "shouldTrim": false
  },
  "frame": {
    "_class": "rect",
    "constrainProportions": false,
    "do_objectID": "04F92EEB-A527-4F5F-83AF-B4031210EBFB",
    "height": 114,
    "width": 90,
    "x": 379,
    "y": 868
  },
  "hasClippingMask": false,
  "horizontalSpacing": 0,
  "isFixedToViewport": false,
  "isFlippedHorizontal": false,
  "isFlippedVertical": false,
  "isLocked": false,
  "isVisible": true,
  "layerListExpandedType": 0,
  "name": "image copy 8",
  "nameIsFixed": false,
  "overrideValues": [
  ],
  "resizingConstraint": 63,
  "resizingType": 0,
  "rotation": 0,
  "scale": 1,
  "shouldBreakMaskChain": false,
  "style": {
    "_class": "style",
    "contextSettings": {
      "_class": "graphicsContextSettings",
      "blendMode": 0,
      "do_objectID": "E8034001-24E9-4C89-B963-F83587C95CE6",
      "opacity": 0.3881603422619048
    },
    "do_objectID": "6B4BA550-D7AE-4E30-A8E6-6AEFFCBD7F90",
    "endMarkerType": 0,
    "miterLimit": 10,
    "startMarkerType": 0,
    "windingRule": 1
  },
  "symbolID": "AB6E2853-435F-426D-930D-1B91F065D682",
  "verticalSpacing": 0
}