{
  "_class": "group",
  "booleanOperation": -1,
  "clippingMaskMode": 0,
  "do_objectID": "98FB504D-D300-4F0F-BA92-61B9A3B6392D",
  "exportOptions": {
    "_class": "exportOptions",
    "do_objectID": "93A101CB-580F-4BD0-9911-D50F5B96D5EA",
    "exportFormats": [
    ],
    "includedLayerIds": [
    ],
    "layerOptions": 0,
    "shouldTrim": false
  },
  "frame": {
    "_class": "rect",
    "constrainProportions": false,
    "do_objectID": "553F70F6-D367-4B0C-91E9-FB1340BA4A90",
    "height": 19,
    "width": 133,
    "x": 1263,
    "y": 82
  },
  "groupLayout": {
    "_class": "MSImmutableFreeformGroupLayout",
    "do_objectID": "8B179617-2D38-4697-879B-CB0096F65FBD"
  },
  "hasClickThrough": false,
  "hasClippingMask": false,
  "isFixedToViewport": false,
  "isFlippedHorizontal": false,
  "isFlippedVertical": false,
  "isLocked": false,
  "isVisible": true,
  "layerListExpandedType": 0,
  "layers": [
    {
      "class": "text",
      "id": "8F61A1FF-FC2B-47FC-BD56-DB5E8716E33F"
    },
    {
      "class": "text",
      "id": "1B557B35-AB5D-46F4-8534-C14DBD5CADC9"
    }
  ],
  "name": "Group",
  "nameIsFixed": false,
  "resizingConstraint": 63,
  "resizingType": 0,
  "rotation": 0,
  "shouldBreakMaskChain": false,
  "style": {
    "_class": "style",
    "contextSettings": {
      "_class": "graphicsContextSettings",
      "blendMode": 0,
      "do_objectID": "01D98B40-3BFB-4053-8533-BE282B8A0F0E",
      "opacity": 0.39
    },
    "do_objectID": "0C7E6E8E-2A25-4A8B-97DC-EF111C071B2C",
    "endMarkerType": 0,
    "miterLimit": 10,
    "startMarkerType": 0,
    "windingRule": 1
  }
}