{
  "_class": "symbolInstance",
  "booleanOperation": -1,
  "clippingMaskMode": 0,
  "do_objectID": "874C60A9-E561-41E3-B3DD-144FA12BA444",
  "exportOptions": {
    "_class": "exportOptions",
    "do_objectID": "6535DC32-992B-416C-9923-FD0D1888701E",
    "exportFormats": [
    ],
    "includedLayerIds": [
    ],
    "layerOptions": 0,
    "shouldTrim": false
  },
  "frame": {
    "_class": "rect",
    "constrainProportions": false,
    "do_objectID": "9CF2B2E5-A3CF-4513-A21B-E6CBE116AF91",
    "height": 114,
    "width": 90,
    "x": 509,
    "y": 867
  },
  "hasClippingMask": false,
  "horizontalSpacing": 0,
  "isFixedToViewport": false,
  "isFlippedHorizontal": false,
  "isFlippedVertical": false,
  "isLocked": false,
  "isVisible": true,
  "layerListExpandedType": 0,
  "name": "image copy 10",
  "nameIsFixed": false,
  "overrideValues": [
  ],
  "resizingConstraint": 63,
  "resizingType": 0,
  "rotation": 0,
  "scale": 1,
  "shouldBreakMaskChain": false,
  "style": {
    "_class": "style",
    "do_objectID": "2F0DE556-2B3A-43AD-8CDD-8224C466D963",
    "endMarkerType": 0,
    "miterLimit": 10,
    "startMarkerType": 0,
    "windingRule": 1
  },
  "symbolID": "AB6E2853-435F-426D-930D-1B91F065D682",
  "verticalSpacing": 0
}