{
  "_class": "symbolInstance",
  "booleanOperation": -1,
  "clippingMaskMode": 0,
  "do_objectID": "766955FF-6521-4F72-9DC5-363DE9B3E735",
  "exportOptions": {
    "_class": "exportOptions",
    "do_objectID": "BA9363EF-12A3-478E-8A6D-E9A02B7ED28F",
    "exportFormats": [
    ],
    "includedLayerIds": [
    ],
    "layerOptions": 0,
    "shouldTrim": false
  },
  "frame": {
    "_class": "rect",
    "constrainProportions": false,
    "do_objectID": "A189789C-1807-48FF-9889-C08F6AA8AFBD",
    "height": 114,
    "width": 90,
    "x": 703,
    "y": 461
  },
  "hasClippingMask": false,
  "horizontalSpacing": 0,
  "isFixedToViewport": false,
  "isFlippedHorizontal": false,
  "isFlippedVertical": false,
  "isLocked": false,
  "isVisible": true,
  "layerListExpandedType": 0,
  "name": "Book Cover Copy 3",
  "nameIsFixed": false,
  "overrideValues": [
  ],
  "resizingConstraint": 63,
  "resizingType": 0,
  "rotation": 0,
  "scale": 1,
  "shouldBreakMaskChain": false,
  "style": {
    "_class": "style",
    "contextSettings": {
      "_class": "graphicsContextSettings",
      "blendMode": 0,
      "do_objectID": "9BEBF3E4-7052-41EA-97F7-B2CDF38329E8",
      "opacity": 0.25634765625
    },
    "do_objectID": "DDDAC26A-BEC3-44F2-9EDC-6703216D7FE7",
    "endMarkerType": 0,
    "miterLimit": 10,
    "startMarkerType": 0,
    "windingRule": 1
  },
  "symbolID": "D7664466-DDCF-4A52-9285-8C206EC192B9",
  "verticalSpacing": 0
}