{
  "_class": "group",
  "booleanOperation": -1,
  "clippingMaskMode": 0,
  "do_objectID": "4C6B81C2-509A-4E68-9472-94BD8736AA03",
  "exportOptions": {
    "_class": "exportOptions",
    "do_objectID": "BDAF80D7-46CC-49E5-8361-F932D89A84E4",
    "exportFormats": [
    ],
    "includedLayerIds": [
    ],
    "layerOptions": 0,
    "shouldTrim": false
  },
  "frame": {
    "_class": "rect",
    "constrainProportions": false,
    "do_objectID": "A22AFF39-A0BC-4076-96DE-F9E09F792ED4",
    "height": 371,
    "width": 358,
    "x": 219,
    "y": 338
  },
  "groupLayout": {
    "_class": "MSImmutableFreeformGroupLayout",
    "do_objectID": "106B6861-7165-47B0-AF55-7C46BAF12B9F"
  },
  "hasClickThrough": false,
  "hasClippingMask": false,
  "isFixedToViewport": false,
  "isFlippedHorizontal": false,
  "isFlippedVertical": false,
  "isLocked": false,
  "isVisible": true,
  "layerListExpandedType": 2,
  "layers": [
    {
      "class": "shapePath",
      "id": "66A99F46-7ABC-451F-A404-8B31C44AEF8B"
    },
    {
      "class": "shapePath",
      "id": "0F87BA2C-46F2-4123-B934-8D274BA05526"
    },
    {
      "class": "shapePath",
      "id": "50486B0A-6DF2-4CFE-9A98-1AB0F73D5417"
    },
    {
      "class": "shapePath",
      "id": "7FA83900-9553-4905-8569-349D321651D5"
    },
    {
      "class": "shapePath",
      "id": "90F8E947-09FC-4A77-A032-831177D3FAC4"
    },
    {
      "class": "shapePath",
      "id": "87AF212B-054A-4115-9E96-44495EB50235"
    },
    {
      "class": "shapePath",
      "id": "B6774C8C-BF97-41CE-92A2-79F2EB898703"
    },
    {
      "class": "shapePath",
      "id": "53CF2D9C-D4B0-4C1A-80FC-D74D9AA15175"
    },
    {
      "class": "rectangle",
      "id": "CBDB130A-E418-4FFF-B701-148AF488C149"
    }
  ],
  "name": "Group",
  "nameIsFixed": false,
  "resizingConstraint": 63,
  "resizingType": 0,
  "rotation": 0,
  "shouldBreakMaskChain": false,
  "style": {
    "_class": "style",
    "do_objectID": "B4B8EE1F-15B8-4932-9623-708D1DAD3B6A",
    "endMarkerType": 0,
    "miterLimit": 10,
    "startMarkerType": 0,
    "windingRule": 1
  }
}