{
  "_class": "bitmap",
  "booleanOperation": -1,
  "clippingMask": "{{0, 0}, {1, 1}}",
  "clippingMaskMode": 0,
  "do_objectID": "E4959774-577E-49A2-8B70-E7DE844A3E92",
  "exportOptions": {
    "_class": "exportOptions",
    "do_objectID": "1C8D9E0C-9CDE-48B5-B199-03E28D8454D7",
    "exportFormats": [
    ],
    "includedLayerIds": [
    ],
    "layerOptions": 0,
    "shouldTrim": false
  },
  "fillReplacesImage": false,
  "frame": {
    "_class": "rect",
    "constrainProportions": true,
    "do_objectID": "3E032258-A912-4A02-A34A-B77B0BF16479",
    "height": 16,
    "width": 16,
    "x": 0,
    "y": 312
  },
  "hasClippingMask": false,
  "image": {
    "_class": "MSJSONFileReference",
    "_ref": "images/a9ff791510a57e4fdc924d2fa0a682e46d3abd4b.png",
    "_ref_class": "MSImageData"
  },
  "intendedDPI": 72,
  "isFixedToViewport": false,
  "isFlippedHorizontal": true,
  "isFlippedVertical": false,
  "isLocked": false,
  "isVisible": true,
  "layerListExpandedType": 0,
  "name": "arrow-point-to-right copy 3",
  "nameIsFixed": false,
  "resizingConstraint": 63,
  "resizingType": 0,
  "rotation": 0,
  "shouldBreakMaskChain": false,
  "style": {
    "_class": "style",
    "contextSettings": {
      "_class": "graphicsContextSettings",
      "blendMode": 0,
      "do_objectID": "B6B4C19A-D52D-4515-83C1-9535CF32A31F",
      "opacity": 0.4724934895833333
    },
    "do_objectID": "6184E15A-ADFC-48FA-8F08-36D05B1809A9",
    "endMarkerType": 0,
    "miterLimit": 10,
    "startMarkerType": 0,
    "windingRule": 1
  }
}